<?xml version="1.0" encoding="UTF-8"?>
<templates id="template" inherit_id="point_of_sale.template">
  <t t-name="PaymentTransactionPopupWidget">
    <div role="dialog" class="modal-dialog">
      <div class="popup">
        <p class="title">Online Payment</p>
        <p class="body"></p>
      </div>
    </div>
  </t>
    <!-- <t t-name="TriposLaneButton">
        <div class='control-button o_lane_button'>
            <i class='fa fa-th-list' role="img" aria-label="Select Lane" title="Select List" />
            <t t-esc='widget.get_current_lane_name()' />

        </div>
    </t> -->



    <t t-extend="PaymentScreenWidget">
        <t t-jquery="span.next" t-operation="before">
            <span class='button pay'>
                Pay by Card <i class='fa fa-credit-card'></i>
            </span>
        </t>
    </t>

    <!-- 
    <t t-name="TriposLaneScreenWidget" t-extend="ReceiptScreenWidget">
        <t t-jquery="div.top-content" t-operation="inner">
            <span class='button back'>
                <i class='fa fa-angle-double-left'></i>
                Back
            </span>
        </t>
    </t> -->

    <t t-extend="PaymentScreen-Paymentlines">
        <t t-jquery=".col-name" t-operation="inner">
            <t t-if="line.cashregister.journal.type === 'bank'">
                <t t-if="line.vantiv_swipe_pending">
                    <div>PLEASE FINISH PAYMENT</div>
                </t>
                <t t-if="! line.vantiv_swipe_pending">
                  <t t-esc='line.name' />
                </t>
            </t>
            <t t-if="line.cashregister.journal.type !== 'bank'">
                <t t-esc='line.name' />
            </t>
        </t>
        <t t-jquery="tbody tr.paymentline.selected">
          this.removeAttr('class');
          this.attr('t-attf-class', 'paymentline selected #{line.vantiv_swipe_pending ? \'o_pos_vantiv_swipe_pending\' : \'\'}');
        </t>
        <t t-jquery="tbody tr.paymentline[t-att-data-cid*='line.cid']">
          this.removeAttr('class');
          this.attr('t-attf-class', 'paymentline #{line.vantiv_swipe_pending ? \'o_pos_vantiv_swipe_pending\' : \'\'}');
        </t>
        <t t-jquery="tbody tr td.col-tendered.edit">
          this.removeAttr('class');
          this.attr('t-attf-class', 'col-tendered edit #{line.vantiv_swipe_pending ? \'o_pos_vantiv_swipe_pending\' : \'\'}');
        </t>
    </t>

</templates>
